gadjo/__init__.py
gadjo/finders.py
gadjo/locale/fr/LC_MESSAGES/django.mo
gadjo/locale/fr/LC_MESSAGES/django.po
gadjo/static/css/_forms.scss
gadjo/static/css/_grid.scss
gadjo/static/css/_hacks.scss
gadjo/static/css/_jqueryui.scss
gadjo/static/css/_opensans.scss
gadjo/static/css/_portal.scss
gadjo/static/css/_utils.scss
gadjo/static/css/_wcs.scss
gadjo/static/css/arrow-down.svg
gadjo/static/css/gadjo.css
gadjo/static/css/gadjo.css.map
gadjo/static/css/gadjo.scss
gadjo/static/css/header-03.jpeg
gadjo/static/css/indicator.gif
gadjo/static/css/texture.png
gadjo/static/css/icons/action-add.hover.png
gadjo/static/css/icons/action-add.small.386ede.png
gadjo/static/css/icons/action-add.small.6f2b92.png
gadjo/static/css/icons/action-add.small.ff375e.png
gadjo/static/css/icons/action-duplicate.hover.png
gadjo/static/css/icons/action-duplicate.small.386ede.png
gadjo/static/css/icons/action-duplicate.small.6f2b92.png
gadjo/static/css/icons/action-duplicate.small.ff375e.png
gadjo/static/css/icons/action-edit.hover.png
gadjo/static/css/icons/action-edit.small.386ede.png
gadjo/static/css/icons/action-edit.small.6f2b92.png
gadjo/static/css/icons/action-edit.small.ff375e.png
gadjo/static/css/icons/action-remove.hover.png
gadjo/static/css/icons/action-remove.small.386ede.png
gadjo/static/css/icons/action-remove.small.6f2b92.png
gadjo/static/css/icons/action-remove.small.ff375e.png
gadjo/static/css/icons/add.large-hover.png
gadjo/static/css/icons/add.large.png
gadjo/static/css/icons/add.small.386ede.png
gadjo/static/css/icons/add.small.6f2b92.png
gadjo/static/css/icons/add.small.ff375e.png
gadjo/static/css/icons/add.small.png
gadjo/static/css/icons/add.small.white.png
gadjo/static/css/icons/agendas.large-hover.png
gadjo/static/css/icons/agendas.large.png
gadjo/static/css/icons/agendas.small.386ede.png
gadjo/static/css/icons/agendas.small.6f2b92.png
gadjo/static/css/icons/agendas.small.ff375e.png
gadjo/static/css/icons/agendas.small.png
gadjo/static/css/icons/agendas.small.white.png
gadjo-1.18.dist-info/AUTHORS
gadjo-1.18.dist-info/COPYING
gadjo-1.18.dist-info/METADATA
gadjo-1.18.dist-info/WHEEL
gadjo-1.18.dist-info/top_level.txt
gadjo-1.18.dist-info/RECORD
